custom_salesforce_bulk/__init__.py
custom_salesforce_bulk/source.py
custom_salesforce_bulk/source_salesforce_bulk.py
custom_salesforce_bulk-0.1.1.dist-info/METADATA
custom_salesforce_bulk-0.1.1.dist-info/WHEEL
custom_salesforce_bulk-0.1.1.dist-info/top_level.txt
custom_salesforce_bulk-0.1.1.dist-info/RECORD
