Metadata-Version: 2.4
Name: custom_salesforce_bulk
Version: 0.1.1
Summary: A custom Salesforce Bulk API connector.
Home-page: https://pypi.org/project/custom-salesforce-bulk/
Author: Your Name
Author-email: your.email@example.com
Classifier: Programming Language :: Python :: 3
Classifier: License :: OSI Approved :: MIT License
Classifier: Operating System :: OS Independent
Requires-Python: >=3.6
Dynamic: author
Dynamic: author-email
Dynamic: classifier
Dynamic: description
Dynamic: description-content-type
Dynamic: home-page
Dynamic: requires-python
Dynamic: summary
